awflow/__init__.py
awflow/schedulers.py
awflow/spec.py
awflow/workflow.py
awflow/bin/__init__.py
awflow/bin/processor.py
awflow-0.1.0.dist-info/LICENSE.txt
awflow-0.1.0.dist-info/METADATA
awflow-0.1.0.dist-info/WHEEL
awflow-0.1.0.dist-info/entry_points.txt
awflow-0.1.0.dist-info/top_level.txt
awflow-0.1.0.dist-info/RECORD
