Metadata-Version: 2.1
Name: awflow
Version: 0.1.0
Summary: Reusable acyclic workflows in Python. Execute code on HPC systems as if you executed them on your laptop!
Home-page: https://github.com/JoeriHermans/awflow
Author: Joeri Hermans, François Rozet, Arnaud Delaunoy
Author-email: joeri@peinser.com
License: BSD license
Project-URL: Documentation, https://github.com/JoeriHermans/awflow
Project-URL: Source, https://github.com/JoeriHermans/awflow
Project-URL: Tracker, https://github.com/JoeriHermans/awflow/issues
Keywords: awflow workflow workflow-engine hpc slurm hpc-tools reproducible-science
Platform: UNKNOWN
Classifier: Development Status :: 2 - Pre-Alpha
Classifier: Intended Audience :: Developers
Classifier: License :: OSI Approved :: BSD License
Classifier: Natural Language :: English
Classifier: Programming Language :: Python :: 3
Classifier: Programming Language :: Python :: 3.7
Classifier: Programming Language :: Python :: 3.8
Classifier: Programming Language :: Python :: 3.9
Classifier: Programming Language :: Python :: 3.10
Requires-Python: >=3.7
License-File: LICENSE.txt
Requires-Dist: cloudpickle
Provides-Extra: dev
Requires-Dist: build ; extra == 'dev'
Requires-Dist: pytest ; extra == 'dev'
Requires-Dist: pytest-cov ; extra == 'dev'
Requires-Dist: sphinx ; extra == 'dev'
Requires-Dist: sphinx-markdown-builder ; extra == 'dev'
Requires-Dist: sphinx-autodoc-typehints ; extra == 'dev'
Requires-Dist: twine ; extra == 'dev'
Provides-Extra: examples
Requires-Dist: numpy ; extra == 'examples'
